{"location": "Varna", "issued_for": "2024-04-15T12:00:00", "horizon_hours": 24, "unit": "C", "run_id": "2026-06-19_11-00-30__h128_l1_L168_lr0.001", "model": "lstm", "forecast": [{"datetime": "2024-04-15T13:00:00", "lstm": 26.623, "persistence": 26.0, "diurnal": 23.0, "climatology": 13.715, "actual": 26.8}, {"datetime": "2024-04-15T14:00:00", "lstm": 26.352, "persistence": 26.0, "diurnal": 23.0, "climatology": 14.016, "actual": 27.2}, {"datetime": "2024-04-15T15:00:00", "lstm": 25.595, "persistence": 26.0, "diurnal": 22.5, "climatology": 14.085, "actual": 26.6}, {"datetime": "2024-04-15T16:00:00", "lstm": 24.657, "persistence": 26.0, "diurnal": 22.0, "climatology": 13.941, "actual": 25.0}, {"datetime": "2024-04-15T17:00:00", "lstm": 23.57, "persistence": 26.0, "diurnal": 20.7, "climatology": 13.583, "actual": 24.1}, {"datetime": "2024-04-15T18:00:00", "lstm": 22.404, "persistence": 26.0, "diurnal": 19.5, "climatology": 12.95, "actual": 22.9}, {"datetime": "2024-04-15T19:00:00", "lstm": 21.285, "persistence": 26.0, "diurnal": 18.1, "climatology": 12.129, "actual": 21.1}, {"datetime": "2024-04-15T20:00:00", "lstm": 20.302, "persistence": 26.0, "diurnal": 15.7, "climatology": 11.1, "actual": 18.8}, {"datetime": "2024-04-15T21:00:00", "lstm": 19.454, "persistence": 26.0, "diurnal": 15.4, "climatology": 10.367, "actual": 18.5}, {"datetime": "2024-04-15T22:00:00", "lstm": 18.658, "persistence": 26.0, "diurnal": 14.8, "climatology": 9.837, "actual": 19.5}, {"datetime": "2024-04-15T23:00:00", "lstm": 17.882, "persistence": 26.0, "diurnal": 15.4, "climatology": 9.363, "actual": 18.5}, {"datetime": "2024-04-16T00:00:00", "lstm": 17.172, "persistence": 26.0, "diurnal": 15.4, "climatology": 9.016, "actual": 17.0}, {"datetime": "2024-04-16T01:00:00", "lstm": 16.562, "persistence": 26.0, "diurnal": 15.0, "climatology": 8.74, "actual": 16.2}, {"datetime": "2024-04-16T02:00:00", "lstm": 16.025, "persistence": 26.0, "diurnal": 14.8, "climatology": 8.468, "actual": 15.9}, {"datetime": "2024-04-16T03:00:00", "lstm": 15.543, "persistence": 26.0, "diurnal": 14.8, "climatology": 8.235, "actual": 16.8}, {"datetime": "2024-04-16T04:00:00", "lstm": 15.094, "persistence": 26.0, "diurnal": 15.1, "climatology": 8.019, "actual": 17.6}, {"datetime": "2024-04-16T05:00:00", "lstm": 14.723, "persistence": 26.0, "diurnal": 15.3, "climatology": 7.827, "actual": 16.8}, {"datetime": "2024-04-16T06:00:00", "lstm": 14.543, "persistence": 26.0, "diurnal": 15.4, "climatology": 7.697, "actual": 16.1}, {"datetime": "2024-04-16T07:00:00", "lstm": 14.758, "persistence": 26.0, "diurnal": 15.2, "climatology": 7.679, "actual": 16.1}, {"datetime": "2024-04-16T08:00:00", "lstm": 15.43, "persistence": 26.0, "diurnal": 17.4, "climatology": 8.637, "actual": 18.7}, {"datetime": "2024-04-16T09:00:00", "lstm": 16.622, "persistence": 26.0, "diurnal": 20.7, "climatology": 10.106, "actual": 21.0}, {"datetime": "2024-04-16T10:00:00", "lstm": 18.141, "persistence": 26.0, "diurnal": 23.4, "climatology": 11.296, "actual": 23.1}, {"datetime": "2024-04-16T11:00:00", "lstm": 19.568, "persistence": 26.0, "diurnal": 25.0, "climatology": 12.392, "actual": 24.8}, {"datetime": "2024-04-16T12:00:00", "lstm": 20.573, "persistence": 26.0, "diurnal": 26.0, "climatology": 13.27, "actual": 26.1}]}