{"run_id": "2026-06-19_09-43-05__h64_l1_L336_lr0.0005_2", "history": [{"epoch": 1, "train_loss": 0.040009, "val_loss": 1.283345, "val_rmse_C": 1.752864}, {"epoch": 2, "train_loss": 0.024185, "val_loss": 1.20934, "val_rmse_C": 1.670177}, {"epoch": 3, "train_loss": 0.023011, "val_loss": 1.166387, "val_rmse_C": 1.625036}, {"epoch": 4, "train_loss": 0.022389, "val_loss": 1.141105, "val_rmse_C": 1.597538}, {"epoch": 5, "train_loss": 0.021933, "val_loss": 1.138805, "val_rmse_C": 1.592213}, {"epoch": 6, "train_loss": 0.021626, "val_loss": 1.141555, "val_rmse_C": 1.600822}, {"epoch": 7, "train_loss": 0.021429, "val_loss": 1.131634, "val_rmse_C": 1.586018}, {"epoch": 8, "train_loss": 0.021213, "val_loss": 1.111083, "val_rmse_C": 1.563001}, {"epoch": 9, "train_loss": 0.021057, "val_loss": 1.127899, "val_rmse_C": 1.575345}, {"epoch": 10, "train_loss": 0.02089, "val_loss": 1.100676, "val_rmse_C": 1.555574}, {"epoch": 11, "train_loss": 0.020779, "val_loss": 1.135753, "val_rmse_C": 1.592033}, {"epoch": 12, "train_loss": 0.020644, "val_loss": 1.108086, "val_rmse_C": 1.557894}, {"epoch": 13, "train_loss": 0.020538, "val_loss": 1.088594, "val_rmse_C": 1.54291}, {"epoch": 14, "train_loss": 0.020474, "val_loss": 1.107003, "val_rmse_C": 1.562105}, {"epoch": 15, "train_loss": 0.020353, "val_loss": 1.100273, "val_rmse_C": 1.555927}, {"epoch": 16, "train_loss": 0.020261, "val_loss": 1.090592, "val_rmse_C": 1.546179}, {"epoch": 17, "train_loss": 0.020194, "val_loss": 1.098894, "val_rmse_C": 1.558843}, {"epoch": 18, "train_loss": 0.020119, "val_loss": 1.081449, "val_rmse_C": 1.535729}, {"epoch": 19, "train_loss": 0.020062, "val_loss": 1.103155, "val_rmse_C": 1.560378}, {"epoch": 20, "train_loss": 0.019911, "val_loss": 1.095704, "val_rmse_C": 1.556244}, {"epoch": 21, "train_loss": 0.019882, "val_loss": 1.099214, "val_rmse_C": 1.558976}, {"epoch": 22, "train_loss": 0.019785, "val_loss": 1.092767, "val_rmse_C": 1.556857}, {"epoch": 23, "train_loss": 0.019711, "val_loss": 1.101924, "val_rmse_C": 1.558443}]}